nonebot_plugin_furryfusion/__init__.py
nonebot_plugin_furryfusion-0.1.5.dist-info/LICENSE
nonebot_plugin_furryfusion-0.1.5.dist-info/METADATA
nonebot_plugin_furryfusion-0.1.5.dist-info/WHEEL
nonebot_plugin_furryfusion-0.1.5.dist-info/top_level.txt
nonebot_plugin_furryfusion-0.1.5.dist-info/RECORD
