Metadata-Version: 2.1
Name: nonebot_plugin_furryfusion
Version: 0.1.5
Summary: 基于NoneBot2进行适配的兽聚动态查询插件
Author-email: Ekac <2396382559@qq.com>
License: MIT
Requires-Python: >=3.9
License-File: LICENSE
Requires-Dist: nonebot2
Requires-Dist: httpx
Requires-Dist: nonebot-adapter-onebot
